{"gallifrey": 1, "videos": 9, "FoodPorn": 2, "NetflixBestOf": 2, "fffffffuuuuuuuuuuuu": 10, "millionairemakers": 1, "GakiNoTsukai": 1, "SFWPornGifs": 1, "technology": 3, "starcraft": 93, "canada": 2, "funny": 8, "CrazyIdeas": 1, "SuperShibe": 1, "HighQualityGifs": 1, "steamdeals": 9, "AdviceAnimals": 10, "malefashionadvice": 1, "todayilearned": 3, "leagueoflegends": 12, "WTF": 5, "nottheonion": 1, "explainlikeimfive": 14, "gaming": 13, "shutupandtakemymoney": 2, "aww": 3, "StreetFighter": 2, "cringepics": 2, "toronto": 25, "Torontoevents": 1, "creepyPMs": 7, "classicrage": 7, "day9": 1, "JapaneseGameShows": 6, "offbeat": 1, "movies": 2, "AskReddit": 4}
