{"MapPorn": 2, "SickAnimation": 1, "dbz": 8, "VHScoverART": 1, "malcolminthemiddle": 1, "nostalgia": 40, "Documentaries": 4, "writing": 1, "HistoryPorn": 3, "Screenwriting": 1, "woahdude": 3, "WTF": 13, "offmychest": 1, "workaholics": 15, "JamesBond": 1, "normalboots": 1, "horror": 4, "JusticePorn": 1, "trees": 2, "smashbros": 1, "gifs": 2, "AbandonedPorn": 1, "90scartoons": 1, "ClassicMetal": 1, "dvdcollection": 2, "AskReddit": 12, "cringe": 1, "gamemusic": 1, "NetflixBestOf": 5, "badMovies": 3, "skateboarding": 2, "depression": 4, "newjersey": 7, "colbertreport": 3, "nightlyshow": 4, "powerrangers": 1, "worldnews": 1, "GuiltyPleasureMusic": 3, "StandUpComedy": 3, "Metal": 6, "creepy": 2, "pics": 3, "TrueReddit": 2, "drunk": 2, "todayilearned": 3, "EarthPorn": 1, "OldSchoolCool": 8, "Drugs": 3, "led_zeppelin": 1, "Shatter": 1, "MetalPorn": 1, "cats": 1, "BeavisAndButthead": 1, "howardstern": 60, "ObscureMedia": 7, "TheCinemassacre": 14, "tipofmytongue": 1, "batman": 2, "VHS": 4, "Psychonaut": 1, "blunderyears": 2, "offbeat": 2, "movies": 16, "fullmoviesonyoutube": 5, "videos": 4, "TrueAskReddit": 1, "IASIP": 4, "Frisson": 2, "southpark": 37, "funny": 4, "ForeverAlone": 1, "self": 1, "IAmA": 6, "criterion": 2, "nottheonion": 4, "announcements": 1, "TheCompletionist": 2, "ACDC": 12, "im14andthisisfunny": 1, "TrueFilm": 6, "cassetteculture": 1, "TimAndEric": 15, "listentothis": 1, "ArnoldSchwarzenegger": 1, "weirdal": 8, "CultCinema": 1}
