{"unitedkingdom": 4, "AnalGW": 1, "TinyTits": 2, "buffy": 11, "incest": 10, "farscape": 17, "spiders": 3, "csharp": 1, "Wales": 5, "technology": 1, "buttplug": 2, "funny": 11, "videos": 1, "WomenOfColor": 5, "GWCouples": 2, "WTF": 1, "GoneWildTube": 1, "TheRedLion": 9, "dirtypenpals": 1, "NSFW_GIF": 1, "celebnsfw": 9, "kyn_wyn_anonymous": 2, "promos": 1, "nsfw_gifs": 3, "LegalTeens": 1, "rugbyunion": 6, "xsmallgirls": 1, "gonewild": 76, "GoneWildPlus": 1, "pics": 3, "gonewildcolor": 67, "asstastic": 1, "AnalLadies": 2, "anal": 1, "software": 8, "Ebony": 1, "OnOff": 1}
