{"pcgaming": 2, "videos": 20, "AsianFilms": 1, "Assistance": 11, "confession": 8, "cocktails": 2, "futuregarage": 17, "Music": 14, "torrents": 4, "Gin": 3, "festivals": 3, "mixes": 2, "funny": 5, "DnB": 4, "travel": 3, "AmsterdamEnts": 31, "IAmA": 4, "ableton": 3, "spain": 1, "WTF": 16, "Jakarta": 4, "secretsanta": 1, "Whatcouldgowrong": 1, "CombatFootage": 1, "tech_house": 10, "electronicmusic": 6, "hiphopheads": 3, "aww": 2, "homemadexxx": 1, "Favors": 2, "JusticePorn": 11, "trees": 8, "movies": 2, "nederlands": 2, "musictheory": 1, "bmx": 1, "thewalkingdead": 1, "DJs": 31, "ukjackin": 2, "trackers": 3, "recipes": 7, "indonesia": 19, "EntFlix": 1, "relationship_advice": 1, "pics": 7, "nononono": 4, "garage": 7, "AskReddit": 6, "watchpeopledie": 2, "germany": 2, "Amsterdam": 114, "CannabisExtracts": 1, "cringe": 5, "bartenders": 2}
