{"StarWars": 1, "Chihuahua": 2, "NoStupidQuestions": 1, "videos": 7, "todayilearned": 6, "Catholicism": 61, "TheSimpsons": 3, "confession": 7, "Rateme": 11, "ExpectationVsReality": 1, "eatsandwiches": 2, "PoliticalDiscussion": 13, "Arkansas": 1, "changemyview": 5, "dataisbeautiful": 3, "smoking": 1, "politics": 4, "tifu": 1, "TumblrAtRest": 3, "funny": 5, "CrazyIdeas": 5, "humor": 2, "thongs": 1, "neckbeardstories": 1, "AdviceAnimals": 30, "Showerthoughts": 2, "niceguys": 2, "MorbidReality": 9, "whitebeauty": 1, "Shitstatistssay": 24, "facebookwins": 1, "introvert": 1, "worldnews": 2, "AgainstAtheismPlus": 1, "SRSsucks": 2, "BlackPeopleTwitter": 1, "asstastic": 1, "LawSchool": 11, "fatlogic": 2, "whiteknighting": 1, "facepalm": 1, "forwardsfromgrandma": 10, "food": 2, "Economics": 41, "assinthong": 2, "OkCupid": 1, "madmen": 1, "nottheonion": 1, "DebateAnAtheist": 1, "kateupton": 1, "MapPorn": 9, "asoiaf": 2, "news": 21, "iamverysmart": 2, "Documentaries": 3, "blunderyears": 2, "lewronggeneration": 13, "gonewild": 3, "r4r": 1, "StormfrontorSJW": 1, "meat": 6, "AgedBeauty": 3, "badlegaladvice": 4, "progun": 2, "TheRedPill": 1, "pics": 5, "Silverbugs": 3, "AskReddit": 22, "TumblrInAction": 8, "lesbians": 1, "PussyPass": 2, "thesopranos": 2, "anal": 1, "ImGoingToHellForThis": 1, "fatpeoplestories": 1, "IWantOut": 1, "betterCallSaul": 6}
