{"photoshop": 1, "mildlyinteresting": 3, "redditrequest": 1, "teenagers": 58, "panoramicsgonewrong": 2, "tumblr": 2, "LongDistance": 3, "technology": 1, "funny": 15, "badAnimation": 1, "TruthOrDareMe": 1, "AdviceAnimals": 2, "Showerthoughts": 3, "picrequests": 1, "leagueoflegends": 10, "WTF": 1, "montageparodies": 1, "iWallpaper": 60, "notinteresting": 1, "LucidDreaming": 1, "aww": 1, "facepalm": 1, "LifeProTips": 1, "bookexchange": 2, "Hedgehog": 16, "pics": 6, "AskReddit": 15, "dontstarve": 1, "beadsprites": 2, "Eyebleach": 5}
