{"snakes": 12, "videos": 4, "DoesAnybodyElse": 4, "cringepics": 12, "fffffffuuuuuuuuuuuu": 5, "sex": 2, "DestructionPorn": 1, "Justrolledintotheshop": 28, "Fallout": 2, "Calgary": 5, "comiccon": 1, "carporn": 1, "relationships": 4, "funny": 7, "ents": 1, "Drugs": 1, "IAmA": 4, "AdviceAnimals": 1, "breakingbad": 1, "meetup": 1, "Autos": 3, "xbox360": 10, "Portal": 4, "Disneyland": 42, "WTF": 5, "entgaming": 2, "reptiles": 7, "HumanPorn": 1, "photography": 1, "disney": 10, "Gore": 5, "tattoos": 2, "electronicmusic": 2, "trashy": 1, "reddit.com": 2, "cars": 3, "Nissan": 14, "snackexchange": 4, "batman": 1, "electricdaisycarnival": 4, "trees": 100, "Shitty_Car_Mods": 1, "promos": 1, "Minecraft": 1, "RageOfBahamut": 2, "dogs": 1, "creepyPMs": 1, "sandiego": 32, "vegetarian": 21, "freebies": 5, "pics": 13, "nosleep": 3, "AskReddit": 7, "guns": 1, "skyrim": 4, "hookah": 6, "cringe": 2, "secretsanta": 1, "Cartalk": 3}
