{"videos": 7, "runescape": 1, "InlineHockey": 2, "Madden": 10, "sex": 1, "TwoXChromosomes": 34, "panthers": 20, "MorbidReality": 1, "FiftyFifty": 2, "canes": 63, "quityourbullshit": 1, "DestinyTheGame": 5, "HistoryPorn": 2, "2007scape": 12, "hockey": 60, "WTF": 13, "Republican": 3, "occupywallstreet": 5, "gaming": 2, "TalesFromRetail": 1, "hockeyplayers": 27, "AntiJokes": 1, "HelpUsFindTyler": 1, "CodAW": 19, "Minecraft": 1, "serialkillers": 1, "watch_dogs": 3, "Gamecocks": 20, "toshpointO": 1, "EA_NHL": 15, "BF_Hardline": 1, "nfl": 12, "CFB": 34, "TheRedPill": 1, "creepy": 5, "4chan": 1, "NHLHUT": 37}
