{"videos": 7, "HPMOR": 15, "WinMyArgument": 1, "adventuretime": 1, "rickandmorty": 1, "DebateAnarchism": 9, "changemyview": 14, "askphilosophy": 5, "politics": 12, "Android": 1, "technology": 4, "TalesFromRetail": 3, "CrazyIdeas": 6, "FutureWhatIf": 1, "skeptic": 1, "Bad_Cop_No_Donut": 1, "WTF": 12, "IAmA": 3, "AskReddit": 159, "pettyrevenge": 4, "TumblrInAction": 15, "rational": 2, "britishproblems": 5, "worldnews": 1, "nonononoyes": 1, "math": 15, "gaming": 5, "introvert": 1, "funny": 4, "aww": 1, "mildlyinfuriating": 1, "movies": 1, "Frugal": 1, "trees": 1, "skyrim": 4, "news": 1, "myevilplan": 1, "IWantToLearn": 2, "WritingPrompts": 1, "dayz": 1, "rage": 3, "Christianity": 1, "ragenovels": 3, "pics": 7, "atheism": 9, "Planetside": 3, "AdviceAnimals": 9, "Shitstatistssay": 1, "sixwordstories": 1, "minimalism": 1, "badmathematics": 1, "Anarcho_Capitalism": 6, "todayilearned": 6}
