{"pcgaming": 8, "h1z1": 1, "videos": 27, "thenetherlands": 6, "todayilearned": 9, "InternetIsBeautiful": 1, "rickandmorty": 1, "upvotegifs": 2, "books": 5, "Music": 6, "dataisbeautiful": 3, "gifs": 9, "RandomActsOfGaming": 11, "Android": 5, "technology": 4, "funny": 24, "OldSchoolCool": 3, "OutOfTheLoop": 7, "unrealengine": 1, "AdviceAnimals": 16, "startrek": 14, "blog": 1, "gamedev": 1, "WTF": 8, "worldnews": 19, "itmejp": 1, "pcmasterrace": 4, "explainlikeimfive": 1, "gaming": 17, "Unity3D": 4, "spaceporn": 1, "Games": 9, "news": 2, "futuresynth": 2, "Yogscast": 1, "worldbuilding": 1, "television": 20, "dayz": 110, "motorcycles": 1, "pics": 13, "movies": 33, "AskReddit": 6, "AskScienceDiscussion": 1, "DayZBulletin": 2, "starcitizen": 3, "history": 1}
