{"insurgency": 2, "circlebroke": 8, "DeepIntoYouTube": 3, "everymanshouldknow": 1, "Foodforthought": 1, "TheForest": 3, "dirtysmall": 1, "BestOfOutrageCulture": 1, "blog": 1, "FifthWorldPics": 1, "hockey": 1, "WTF": 16, "YouShouldKnow": 1, "JusticePorn": 3, "trees": 4, "geek": 4, "Jokes": 2, "iamverysmart": 7, "Steam": 1, "gifs": 6, "IWantToLearn": 1, "trackers": 2, "4chan": 8, "AskReddit": 10, "SubredditDrama": 20, "Music": 3, "cringe": 15, "mildlyinteresting": 1, "pcgaming": 1, "circlebroke2": 25, "memes": 2, "mathrock": 2, "TwoXChromosomes": 6, "shitpost": 1, "Android": 3, "badphilosophy": 2, "space": 1, "skeptic": 1, "Freethought": 1, "UnexpectedThugLife": 1, "HeroesandGenerals": 1, "worldnews": 2, "pcmasterrace": 8, "blackpeoplegifs": 2, "bestof": 2, "circlejerk": 4, "NotTimAndEric": 3, "Frugal": 1, "news": 7, "youtubehaiku": 12, "dayz": 2, "creepy": 2, "pics": 18, "Planetside": 1, "itookapicture": 1, "GameDeals": 1, "betterCallSaul": 3, "QuotesPorn": 1, "TrueReddit": 5, "todayilearned": 10, "reactiongifs": 3, "republicwireless": 2, "TrollXChromosomes": 1, "buttmusic": 1, "Guitar": 2, "spam": 3, "OutOfTheLoop": 7, "MorbidReality": 4, "cats": 1, "ifyoulikeblank": 2, "oldpeoplefacebook": 2, "explainlikeimfive": 1, "arma": 1, "mildlyinfuriating": 1, "LifeProTips": 1, "skyrim": 4, "twinks": 8, "blunderyears": 1, "television": 2, "pathofexile": 1, "rage": 1, "comics": 1, "science": 1, "offbeat": 4, "movies": 4, "standupshots": 3, "EVEX": 2, "hacking": 1, "NewsOfTheStupid": 1, "videos": 32, "redditdonate": 1, "politics": 1, "technology": 9, "instantbarbarians": 1, "IAmA": 6, "nottheonion": 5, "gaming": 9, "paydaytheheist": 1, "aww": 4, "askscience": 1, "philosophy": 1, "Games": 1, "EnoughLibertarianSpam": 3, "Upskirt": 2, "atheism": 5, "me_irl": 14, "EvolveGame": 2, "ImGoingToHellForThis": 2}
