{"videos": 2, "gaming": 7, "nostalgia": 4, "politics": 1, "technology": 2, "AnimatedLadyBoners": 3, "TheLastAirbender": 116, "BeardPorn": 2, "funny": 10, "gameofthrones": 5, "tomhiddleston": 31, "wow": 2, "IAmA": 2, "AskReddit": 24, "WTF": 15, "worldnews": 2, "disney": 3, "TrueBlood": 3, "eyes": 2, "tattoos": 1, "aww": 8, "askscience": 2, "trees": 3, "NigelThornberry": 1, "LadyBoners": 34, "chesthairporn": 1, "doctorwho": 17, "beards": 1, "GVSU": 2, "TheHobbit": 2, "steampunk": 1, "pics": 10, "atheism": 14, "AdviceAnimals": 8, "Sherlock": 8, "ladybonersgw": 1}
