{"buildapc": 13, "gamingpc": 10, "videos": 4, "audiophile": 9, "electronic_cigarette": 24, "canon": 3, "sysadmin": 1, "amiga": 10, "pcgaming": 2, "ConfessionBear": 1, "Diablo3Crusaders": 5, "quityourbullshit": 1, "shittyfoodporn": 1, "AdviceAnimals": 2, "Documentaries": 1, "justneckbeardthings": 1, "CableManagement": 18, "shittybattlestations": 1, "retrobattlestations": 3, "pcmasterrace": 22, "talesfromtechsupport": 1, "gaming": 1, "Vaping101": 1, "aww": 7, "reactiongifs": 1, "photography": 7, "BestOfBaPC": 17, "LifeProTips": 1, "skyrim": 1, "news": 1, "overclocking": 1, "audio": 1, "Blep": 1, "audiorepair": 1, "diyaudio": 4, "Surface": 3, "pics": 1, "movies": 1, "AskReddit": 41, "quittingkratom": 6, "itookapicture": 5, "Seattle": 1, "retrogaming": 4, "BudgetAudiophile": 10, "hometheater": 57}
