{"pcgaming": 10, "TrueReddit": 1, "technology": 1, "xkcd": 2, "TumblrAtRest": 3, "forwardsfromgrandma": 14, "im14andthisisfunny": 8, "cozystations": 2, "ofcourseyoudont": 1, "ShitCosmoSays": 3, "shittybattlestations": 12, "Fallout": 12, "im14andthisisdeep": 9, "pcmasterrace": 195, "bigbangcomics": 2, "skyrimmods": 6, "circlejerk": 3, "NotTimAndEric": 2, "movies": 1, "Games": 8, "skyrim": 22, "magicskyfairy": 2, "TiADiscussion": 1, "Steam": 14, "Braveryjerk": 12, "fnv": 6, "thatHappened": 24, "steamdeals": 2, "terriblefacebookmemes": 4, "AskReddit": 24, "TumblrInAction": 199, "me_irl": 10, "consolemasterrace": 1, "FellowKids": 5, "GameDeals": 1, "battlestations": 3}
