{"buildapc": 3, "MightyNo9": 1, "Music": 1, "torrents": 2, "wiiu": 1, "vita": 2, "assassinscreed": 3, "pokemon": 8, "PS4": 24, "HIMYM": 1, "poppunkers": 1, "AmericanHorrorStory": 4, "IAmA": 1, "zelda": 17, "LearnJapanese": 3, "writing": 1, "Rainmeter": 4, "thewalkingdead": 1, "britishproblems": 3, "iphone": 4, "3DS": 27, "Games": 110, "elderscrollsonline": 7, "Hannibal": 1, "Steam": 2, "infamous": 1, "Essex": 1, "movies": 32, "AskReddit": 37, "anime": 24, "arrow": 3, "ScottPilgrim": 1, "GameDeals": 2}
