{"Whatisthis": 1, "phillycycling": 9, "whatisthisthing": 2, "MechanicalKeyboards": 7, "Delaware": 1, "vine": 1, "vim": 3, "mutt": 1, "Foodforthought": 2, "warcraft2": 1, "linguistics": 2, "TrueReddit": 1, "AskHistorians": 1, "bicycling": 2, "IAmA": 2, "philadelphia": 209, "Documentaries": 1, "zappafied": 1, "PenmanshipPorn": 1, "phillyairforce": 1, "dogs": 56, "node": 1, "StandUpComedy": 1, "ween": 4, "funny": 1, "Pennsylvania": 1, "commandline": 4, "javascript": 17, "Frugal": 1, "promos": 1, "baseball": 13, "MapPorn": 2, "dogpictures": 4, "aviation": 3, "Blackmouthcur": 1, "webcomics": 1, "youtubehaiku": 4, "riddles": 1, "bicycletouring": 3, "enlightenedbirdmen": 2, "uhhyeahdude": 27, "vexillology": 8, "OaklandAthletics": 1, "chinook": 8, "phillies": 11}
