{"turtle": 23, "fullmoviesonyoutube": 1, "rva": 6, "Proasheck": 1, "videos": 7, "Yogscast": 42, "todayilearned": 6, "lorde": 8, "mildlyinteresting": 1, "friendsafari": 7, "sips": 18, "asoiaf": 1, "tifu": 3, "ImaginaryLeviathans": 1, "pokemon": 9, "homestuck": 11, "TumblrAtRest": 1, "trendingsubreddits": 1, "asmr": 12, "DieAntwoord": 3, "technology": 2, "SquaredCircle": 7, "IAmA": 1, "AskReddit": 27, "Showerthoughts": 3, "writing": 10, "malefashionadvice": 1, "craigslist": 1, "leagueoflegends": 1, "WTF": 6, "worldnews": 3, "TheDarkTower": 6, "gaming": 10, "logophilia": 2, "funny": 14, "swtor": 26, "gamegrumps": 10, "JusticePorn": 5, "PointlessStories": 1, "JonTron": 1, "aww": 1, "Warhammer": 2, "skyrim": 8, "FastWorkers": 1, "videogamedunkey": 32, "pokemontrades": 13, "Minecraft": 8, "twitchplayspokemon": 2, "worldbuilding": 18, "GameTheorists": 1, "Pareidolia": 1, "SketchDaily": 1, "pics": 6, "movies": 6, "AdviceAnimals": 7, "science": 2, "ConspiracyGrumps": 11, "wow": 4, "ShitLewisSays": 2}
