{"mildlyinteresting": 7, "AskScienceFiction": 2, "Justrolledintotheshop": 15, "todayilearned": 1, "mazda3": 8, "mazda": 5, "patientgamers": 3, "gadgets": 6, "subaru": 10, "futurama": 1, "startrek": 1, "rally": 2, "Android": 9, "Dogtraining": 2, "technology": 5, "tifu": 1, "funny": 4, "techsupportmacgyver": 1, "kol": 1, "lego": 2, "boardgames": 1, "IAmA": 1, "AdviceAnimals": 5, "Showerthoughts": 8, "Nexus5": 5, "scifi": 2, "WTF": 1, "askscience": 5, "pcmasterrace": 139, "explainlikeimfive": 1, "adventuretime": 2, "ObscureMedia": 1, "gaming": 3, "dogs": 2, "aww": 4, "cars": 5, "facepalm": 15, "ECE": 3, "Volvo": 9, "geek": 1, "Games": 2, "interestingasfuck": 2, "Shitty_Car_Mods": 14, "photoshopbattles": 1, "keto": 1, "techsupportgore": 1, "Chromecast": 3, "Edmonton": 15, "space": 1, "engineering": 2, "Surface": 10, "pics": 5, "movies": 1, "AskReddit": 50, "books": 3, "HomestarRunner": 1, "UserCars": 4, "starcitizen": 2, "Cartalk": 8}
