{"europe": 12, "asoiaf": 2, "firefox": 4, "TrueReddit": 12, "AskWomen": 2, "todayilearned": 13, "linux4noobs": 3, "askphilosophy": 6, "coding": 4, "bestof": 13, "books": 2, "linux": 37, "spacex": 7, "webdev": 1, "technology": 16, "javaTIL": 3, "BasicIncome": 1, "java": 1, "privacy": 4, "fossworldproblems": 1, "communism101": 1, "computerscience": 2, "IAmA": 3, "blog": 2, "Economics": 9, "socialism": 33, "opensource": 1, "Ubuntu": 4, "worldnews": 12, "tech": 12, "CriticalTheory": 1, "explainlikeimfive": 10, "PushBullet": 3, "polandball": 3, "nutrition": 2, "Anarchism": 6, "jobs": 4, "askscience": 3, "Futurology": 3, "philosophy": 28, "ProgrammingDiscussion": 11, "thelastpsychiatrist": 5, "educationalgifs": 2, "promos": 2, "Supplements": 1, "ImaginaryWesteros": 2, "EnoughLibertarianSpam": 3, "Fitness": 5, "news": 7, "DepthHub": 12, "ProgrammerHumor": 4, "Romania": 2, "comics": 1, "science": 1, "programming": 20, "politics": 4, "skeptic": 1, "AskReddit": 21, "compsci": 1, "croatia": 3, "SPACECOMMUNISM": 2, "Anarcho_Capitalism": 26, "rust": 3}
