{"HotlineMiami": 3, "youdontsurf": 1, "Alexelcapoyt": 19, "Music": 2, "linux": 44, "shitpost": 3, "linuxmemes": 1, "PS4": 1, "funny": 2, "ReviewsOfAnything": 1, "micronofap": 1, "IAmA": 1, "AdviceAnimals": 1, "Steam": 2, "archlinux": 1, "woahdude": 2, "pcmasterrac": 2, "admincraft": 7, "outrun": 4, "LinuxCirclejerk": 7, "gaming": 1, "MotoG": 6, "intrusivethoughts": 3, "aww": 1, "unturned": 33, "circlejerk": 86, "spanishgamedev": 1, "Jokes": 4, "linux_gaming": 15, "WritingPrompts": 3, "NoStupidQuestions": 1, "Minecraft": 1, "starboundcirclejerk": 1, "spain": 1, "Unexpected": 2, "4ChanMeta": 1, "spongeproject": 2, "hacking": 3, "creepy": 3, "listentoobscure": 1, "AskReddit": 45, "FullmetalAlchemist": 1, "PCMRProblems": 1, "pcmasterrace": 90, "GameDeals": 1, "evangelion": 4, "dongerlounge": 9}
