{"mildlyinteresting": 1, "LifeProTips": 1, "videos": 8, "todayilearned": 21, "cringepics": 3, "interestingasfuck": 2, "Music": 1, "politics": 1, "technology": 4, "funny": 9, "CrazyIdeas": 1, "movies": 1, "thebutton": 1, "IAmA": 2, "AskReddit": 11, "sports": 11, "aww": 1, "shittyreactiongifs": 4, "WTF": 1, "worldnews": 8, "holdmybeer": 1, "gaming": 4, "facepalm": 2, "food": 4, "batman": 2, "JusticePorn": 1, "oddlysatisfying": 1, "baseball": 1, "Psychonaut": 1, "BlackPeopleTwitter": 2, "aviation": 2, "illusionporn": 1, "gifs": 8, "rage": 1, "science": 3, "space": 3, "woahdude": 1, "pics": 14, "4chan": 3, "AdviceAnimals": 1, "Tinder": 1, "cringe": 1}
