{"Heavymind": 1, "MapPorn": 9, "adventuretime": 1, "KitchenConfidential": 1, "futurama": 1, "everymanshouldknow": 3, "dataisbeautiful": 5, "relationships": 2, "Showerthoughts": 2, "harrypotter": 2, "HistoryPorn": 5, "whowouldwin": 1, "woahdude": 11, "WTF": 2, "CityPorn": 1, "LosAngeles": 4, "Judaism": 3, "gifs": 6, "photography": 1, "nottheonion": 6, "cringepics": 2, "beards": 1, "Steam": 2, "photoshopbattles": 4, "CrappyDesign": 1, "AskReddit": 37, "mildlyinteresting": 8, "pcgaming": 1, "EatCheapAndHealthy": 1, "Christianity": 2, "interestingasfuck": 1, "books": 1, "changemyview": 1, "writing": 4, "psychology": 2, "Entrepreneur": 2, "skeptic": 2, "AskNYC": 1, "InteriorDesign": 1, "AdviceAnimals": 8, "breakingbad": 1, "malefashionadvice": 2, "outside": 2, "worldnews": 6, "lifehacks": 2, "facepalm": 2, "AnimalCrossing": 2, "news": 1, "DepthHub": 1, "RedditDayOf": 2, "personalfinance": 3, "pics": 29, "Design": 1, "battlestations": 8, "GetMotivated": 2, "buildapc": 3, "apple": 4, "todayilearned": 21, "confession": 4, "reactiongifs": 2, "Buddhism": 2, "TrollXChromosomes": 1, "tifu": 3, "roadtrip": 1, "pokemon": 8, "blog": 1, "OldSchoolCool": 1, "AskHistorians": 7, "explainlikeimfive": 15, "Diablo": 1, "3DS": 3, "oddlysatisfying": 1, "birdswitharms": 1, "LifeProTips": 6, "sex": 1, "darksouls": 6, "science": 10, "movies": 5, "civ": 3, "Meditation": 1, "history": 2, "windowsphone": 1, "videos": 4, "FoodPorn": 5, "Cooking": 1, "politics": 2, "babyelephantgifs": 1, "funny": 32, "IAmA": 2, "scifi": 4, "spaceporn": 1, "nyc": 3, "talesfromtechsupport": 3, "gaming": 20, "aww": 3, "askscience": 4, "Futurology": 6, "Games": 2, "Minecraft": 2, "alcohol": 1, "HumanPorn": 2}
