{"houston": 2, "gardening": 1, "FoodPorn": 1, "todayilearned": 4, "Fitness": 3, "sex": 5, "Music": 1, "roosterteeth": 3, "AnythingGoesNews": 1, "politics": 2, "pics": 3, "funny": 1, "Hotchickswithtattoos": 1, "WTF": 2, "nottheonion": 1, "bicycletouring": 2, "spaceengineers": 17, "anime": 2, "tattoos": 1, "runforyourlives": 2, "tattoo": 1, "NSFW_GIF": 1, "running": 7, "bigdickproblems": 3, "Lufkin": 20, "news": 1, "thewalkingdead": 5, "RWBY": 1, "r4r": 4, "Art": 2, "relationship_advice": 1, "podcasts": 7, "AskReddit": 57, "TrueAtheism": 2, "zombies": 3, "Nacogdoches": 2, "runningmusic": 1, "malefashionadvice": 1, "RedditForGrownups": 1}
