{"glassblowing": 1, "Blink182": 31, "videos": 6, "todayilearned": 2, "millionairemakers": 35, "Club_Nintendo": 2, "bestof": 1, "Music": 9, "treesmovienight": 1, "breakingbad": 1, "technology": 1, "HouseOfCards": 5, "funny": 26, "astrophotography": 4, "instant_regret": 2, "AMA": 1, "IAmA": 37, "Showerthoughts": 1, "amiibo": 27, "cats": 6, "woahdude": 2, "WTF": 5, "itookapicture": 1, "holidaybullshit": 16, "gaming": 5, "Frisson": 5, "casualiama": 12, "horror": 5, "trees": 19, "AnimalCrossing": 14, "oddlysatisfying": 2, "Games": 2, "Random_Acts_Of_Pizza": 62, "MNAmiiboHunters": 3, "AskMen": 8, "beermoney": 2, "TrueDetective": 3, "TimAndEric": 4, "pics": 9, "movies": 20, "AskReddit": 19, "secretsanta": 3, "rickandmorty": 1, "wilfred": 1, "NewNintendo3DSXL": 1, "musicforsex": 1, "betterCallSaul": 1}
