{"Paleo": 1, "glutenfreevegan": 1, "CryptoAnarchy": 2, "todayilearned": 10, "Transhuman": 2, "Bitcoin": 31, "proxies": 1, "intj": 8, "anarchafeminism": 2, "Anarchism": 49, "MechanicAdvice": 3, "EarthPorn": 3, "WikiLeaks": 3, "Android": 1, "pics": 4, "technology": 3, "glutenfree": 8, "DebateAnarchism": 8, "DesirePath": 1, "Agorism": 5, "AskHistorians": 3, "onions": 3, "IAmA": 3, "TheFacebookDelusion": 5, "artificial": 4, "elementaryos": 4, "TOR": 3, "PenmanshipPorn": 1, "AdviceAnimals": 4, "WTF": 2, "Ubuntu": 2, "worldnews": 8, "Nexus5": 10, "explainlikeimfive": 5, "vexillology": 4, "anarchistpics": 5, "n64": 6, "BasicIncome": 1, "gifs": 2, "askscience": 3, "Futurology": 6, "SocialEngineering": 2, "transhumanism": 7, "oddlysatisfying": 1, "HackBloc": 2, "Celiac": 27, "SilkRoad": 2, "news": 7, "singularity": 5, "anarchotranshumanist": 2, "anarchomemes": 5, "ShittyMapPorn": 2, "soylent": 1, "veganarchism": 1, "libertyworldproblems": 1, "science": 2, "realsocialengineering": 3, "PropagandaPosters": 4, "CrappyDesign": 1, "atheism": 16, "Entrepreneur": 2, "AskReddit": 60, "Shitstatistssay": 5, "Jobs4Bitcoins": 13, "futuristparty": 13, "bestof": 5, "Bad_Cop_No_Donut": 1, "Music": 5}
