{"videos": 1, "todayilearned": 13, "tumblr": 2, "Music": 1, "tifu": 1, "technology": 2, "homestuck": 8, "funny": 41, "thebutton": 1, "AskReddit": 56, "worldnews": 8, "pcmasterrace": 1, "explainlikeimfive": 4, "gaming": 2, "aww": 1, "askscience": 1, "UpliftingNews": 1, "trees": 1, "IDontWorkHereLady": 2, "LifeWithIgor": 1, "LifeProTips": 1, "BlackPeopleTwitter": 1, "news": 9, "Marvel": 1, "gifs": 12, "WritingPrompts": 1, "pics": 7, "atheism": 4, "movies": 1, "AdviceAnimals": 35, "TumblrInAction": 1, "DotA2": 3, "ImGoingToHellForThis": 1}
