{"mildlyinteresting": 4, "videos": 2, "Alienware": 6, "todayilearned": 29, "metaldetecting": 2, "Pensacola": 11, "buildapc": 1, "milf": 2, "interestingasfuck": 1, "Health": 1, "torrents": 3, "politics": 1, "Deathmetal": 2, "CraftBeer": 1, "funny": 18, "kansascity": 99, "truegaming": 1, "entertainment": 5, "skeptic": 1, "JoeRogan": 4, "RealGirls": 3, "AdviceAnimals": 5, "craigslist": 4, "4hourbodyslowcarb": 1, "Gore": 2, "WTF": 17, "HomeImprovement": 20, "Hardcore": 1, "KCjobs": 2, "Whatcouldgowrong": 1, "woahdude": 2, "gaming": 3, "food": 1, "collapse": 3, "AlienwareAlpha": 2, "Metal": 18, "AMA": 2, "Terraria": 1, "Frugal": 13, "emulation": 7, "LifeProTips": 1, "xbox360": 3, "news": 6, "worldnews": 1, "4Runner": 9, "smodcast": 1, "chrome": 1, "gifs": 2, "science": 1, "Lawrence": 1, "BuyItForLife": 6, "pics": 16, "offbeat": 4, "movies": 17, "AskReddit": 39, "watchpeopledie": 3, "GameDeals": 1, "everymanshouldknow": 2, "RealEstate": 2, "DIY": 7}
