{"relationship_advice": 1, "fullmoviesonyoutube": 3, "awwwtf": 2, "whatisthisthing": 5, "videos": 27, "DoesAnybodyElse": 1, "todayilearned": 5, "PublicFreakout": 1, "confession": 2, "reactiongifs": 1, "QuotesPorn": 1, "TrueAskReddit": 1, "sex": 5, "RoomPorn": 1, "Showerthoughts": 1, "InternetIsBeautiful": 1, "nononono": 4, "blues": 1, "CrazyIdeas": 1, "news": 3, "answers": 1, "uniformporn": 1, "write": 1, "gameofthrones": 1, "humor": 1, "OldSchoolCool": 2, "OCPoetry": 4, "Advice": 3, "BodyAcceptance": 1, "IAmA": 10, "nostalgia": 1, "Documentaries": 1, "breakingbad": 1, "HistoryPorn": 6, "StonerEngineering": 1, "Foodforthought": 1, "amateurfights": 1, "AskCulinary": 1, "WTF": 18, "4chan": 2, "worldnews": 6, "explainlikeimfive": 4, "woahdude": 3, "CombatFootage": 1, "TheWayWeWere": 1, "MilitaryPorn": 1, "sushi": 2, "ExpectationVsReality": 1, "funny": 10, "aww": 4, "horror": 1, "JusticePorn": 3, "IWantToLearn": 5, "trees": 2, "fightporn": 1, "lgbt": 1, "WritingPrompts": 2, "food": 1, "drums": 3, "cringepics": 6, "BestOfLiveleak": 3, "AskMen": 6, "ThriftStoreHauls": 2, "gifs": 2, "socialskills": 1, "MachinePorn": 1, "grammar": 1, "creepyPMs": 3, "showerbeer": 4, "Jokes": 3, "thatHappened": 1, "mspaintbattles": 1, "florida": 1, "Stoicism": 1, "Watches": 2, "pics": 12, "WeAreTheMusicMakers": 1, "movies": 3, "AskReddit": 186, "socialism": 1, "minimalism": 1, "cringe": 2, "GetMotivated": 1, "AdPorn": 1, "everymanshouldknow": 2}
