{"mildlyinteresting": 1, "dataisbeautiful": 3, "videos": 12, "todayilearned": 9, "Lubbock": 8, "CityPorn": 1, "SuddenlyClinton": 1, "QuotesPorn": 1, "FunnyandSad": 1, "millionairemakers": 1, "engineering": 1, "AdviceAnimals": 10, "Automate": 1, "TrollXChromosomes": 1, "politics": 3, "CrappyDesign": 1, "technology": 10, "firstworldanarchists": 4, "funny": 17, "DunderMifflin": 2, "TrueReddit": 1, "lego": 1, "seduction": 1, "IAmA": 2, "NotTimAndEricPics": 1, "sports": 1, "MorbidReality": 3, "woahdude": 1, "WTF": 8, "askscience": 5, "worldnews": 4, "gaming": 4, "downtimebananas": 1, "TexasTech": 5, "gonewild": 1, "food": 1, "reactiongifs": 1, "Futurology": 1, "trees": 3, "fffffffuuuuuuuuuuuu": 1, "Homebrewing": 1, "Antiques": 2, "news": 3, "gifs": 7, "youtubehaiku": 1, "motorcycles": 1, "comics": 1, "science": 4, "TheRedPill": 2, "pics": 15, "atheism": 3, "movies": 4, "AskReddit": 22, "compsci": 1, "Enhancement": 1, "Libertarian": 2, "sloths": 1, "AskEngineers": 15, "cringe": 1, "Radiolab": 1}
