{"buildapc": 1, "whatisthisthing": 2, "MechanicalKeyboards": 2, "drunk": 1, "catpranks": 4, "boston": 3, "Fitness": 2, "millionairemakers": 4, "tumblr": 2, "books": 1, "changemyview": 1, "DessertPorn": 1, "ContagiousLaughter": 2, "tf2": 10, "funny": 9, "videos": 2, "ECR_Gaming": 1, "tattoos": 1, "AskWomen": 2, "ExpectationVsReality": 1, "todayilearned": 1, "AdviceAnimals": 5, "shittyrobots": 1, "starcraft": 6, "gaming": 22, "JusticePorn": 2, "askscience": 1, "facepalm": 6, "fatlogic": 2, "AnimalCrossing": 15, "LifeProTips": 5, "cringepics": 3, "sex": 1, "lewronggeneration": 1, "gifs": 6, "riddles": 1, "science": 4, "standupshots": 15, "pics": 22, "movies": 1, "AskReddit": 13, "TumblrInAction": 4, "silenthill": 8, "battlestations": 2, "self": 1}
