{"Smite": 19, "gallifrey": 2, "pcgaming": 48, "softwareswap": 1, "Connery": 1, "todayilearned": 2, "millionairemakers": 1, "TalesFromRetail": 1, "pokemon": 1, "GlobalOffensive": 7, "dueprocess": 1, "IAmA": 2, "outside": 5, "paydaybuilds": 3, "IntenseConversation": 1, "hockey": 1, "pcmasterrace": 105, "explainlikeimfive": 1, "montageparodies": 2, "gaming": 6, "paydaytheheist": 9, "LiquidSky": 3, "Prismata": 1, "snackexchange": 1, "WarplanePorn": 3, "explainlikeimelected": 1, "nerdcubed": 3, "Fitness": 1, "stanisms": 1, "Steam": 2, "buildapcforme": 6, "gifs": 2, "WritingPrompts": 7, "VentGrumps": 1, "Planetside2Air": 2, "Planetside": 41, "AskReddit": 31, "dogetipbot": 2, "dogecoin": 20, "SubredditDrama": 2, "CasualConversation": 72, "paradoxplaza": 4}
