{"FancyFollicles": 2, "morbidlybeautiful": 1, "vikingsgonewild": 1, "gardening": 1, "whatisthisthing": 1, "AskWomen": 21, "todayilearned": 1, "NarcissisticAbuse": 1, "redditgetsdrawn": 2, "NewsPorn": 2, "TwoXChromosomes": 1, "Veterans": 4, "footbaww": 1, "trashy": 2, "CrossStitch": 1, "funny": 4, "AnimalsBeingJerks": 2, "movies": 2, "IconicImages": 1, "AmericanHorrorStory": 1, "AdviceAnimals": 2, "pugs": 3, "Parenting": 1, "PenmanshipPorn": 1, "woahdude": 1, "RandomActsofCards": 2, "worldnews": 3, "lifehacks": 1, "MineralPorn": 1, "trashyboners": 2, "quilting": 1, "MandelaEffect": 1, "succulents": 1, "aww": 7, "askscience": 2, "LetsNotMeet": 1, "DumpsterDiving": 2, "Thetruthishere": 1, "raisedbynarcissists": 6, "LadyBoners": 4, "curlyhair": 1, "whatsthisplant": 4, "rockhounds": 1, "MapPorn": 2, "Unexpected": 2, "Art": 1, "pics": 5, "Glitch_in_the_Matrix": 1, "AskReddit": 32, "lastimages": 1, "thalassophobia": 1, "minimalism": 1, "Moviesinthemaking": 1, "LifeProTips": 2}
