{"Piracy": 1, "runescape": 1, "Bitcoin": 7, "BuyItForLife": 4, "perfectloops": 3, "Foodforthought": 5, "DubbedGIFS": 3, "financialindependence": 1, "TheoryOfReddit": 1, "WorldofTanks": 2, "virtualreality": 1, "fireTV": 1, "Frisson": 2, "ScenesFromAHat": 2, "ofcoursethatsathing": 1, "quiteinteresting": 2, "Steam": 5, "itsaunixsystem": 3, "badcode": 2, "Djent": 2, "AskReddit": 8, "compsci": 4, "google": 4, "TrueAtheism": 2, "NetflixBestOf": 1, "samfrancisco": 1, "Entrepreneur": 2, "SelfDrivingCars": 2, "books": 2, "changemyview": 9, "Android": 1, "startups": 1, "TumblrAtRest": 1, "heroesofthestorm": 4, "skeptic": 7, "wikipedia": 9, "Freethought": 1, "starbound": 1, "bestof": 4, "Metal": 8, "NotTimAndEric": 3, "careerguidance": 1, "GamePhysics": 3, "DepthHub": 4, "Ingress": 5, "sanfrancisco": 12, "programming": 10, "bayarea": 2, "dogecoin": 2, "wheredidthesodago": 3, "GameDeals": 2, "betterCallSaul": 1, "gamingpc": 1, "apple": 2, "orbo": 1, "IdiotsFightingThings": 1, "nosurf": 1, "shutdown": 1, "linux": 5, "discworld": 3, "TheFutureIsNow": 1, "tf2": 2, "kol": 1, "lowendgaming": 1, "chrome": 1, "devops": 2, "programminghorror": 4, "California": 11, "NotFoolingAnybody": 1, "WTF": 1, "3DS": 2, "androidapps": 1, "cordcutters": 2, "Cordcutting": 1, "Buttcoin": 4, "science": 7, "Flipping": 1, "movies": 1, "BritishTV": 1, "RedditForGrownups": 1, "fullmoviesonyoutube": 1, "FearMe": 1, "sysadmin": 4, "lolphp": 1, "DIY": 1, "brokengifs": 1, "webdev": 3, "atheism": 1, "HighQualityGifs": 5, "self": 7, "progmetal": 2, "getdisciplined": 1, "breathinginformation": 1, "TechnicalDeathMetal": 1, "aww": 1, "Games": 1, "hearthstone": 5, "Minecraft": 2, "oculus": 3, "science2": 1, "DataHoarder": 2}
