{"talesfromtechsupport": 1, "mildlyinteresting": 1, "ghibli": 4, "videos": 3, "todayilearned": 1, "gadgets": 4, "KDCGameGrumps": 2, "interestingasfuck": 1, "books": 5, "Music": 2, "ImaginaryLandscapes": 2, "EarthPorn": 1, "gifs": 3, "nintendomusic": 1, "technology": 3, "firstworldanarchists": 3, "asmr": 15, "FiftyFifty": 1, "CrazyIdeas": 3, "TrueReddit": 1, "thebutton": 1, "altnames": 2, "ShortSadStories": 1, "writing": 1, "Overgrowth": 1, "whowouldwin": 7, "woahdude": 4, "WTF": 3, "ImaginaryMonsters": 3, "nottheonion": 1, "firefly": 3, "gaming": 2, "misleadingthumbnails": 1, "funny": 4, "askscience": 1, "gamegrumps": 42, "smashbros": 3, "Showerthoughts": 2, "Games": 1, "SimplePrompts": 4, "news": 1, "iamverysmart": 1, "Physics": 3, "promptoftheday": 2, "Lightbulb": 1, "worldbuilding": 2, "WritingPrompts": 1, "Art": 2, "movies": 2, "AskReddit": 15, "nerdfighters": 1}
