{"buildapc": 1, "Slender_Man": 4, "videos": 12, "NorthKoreaNews": 1, "subaru": 6, "weather": 9, "DestructionPorn": 1, "FiestaST": 1, "carporn": 4, "funny": 4, "gameofthrones": 2, "IAmA": 1, "Volkswagen": 6, "minecraftROK": 3, "beer": 1, "BMW": 6, "WTF": 5, "worldnews": 2, "CatsStandingUp": 1, "wallpapers": 2, "talesfromtechsupport": 1, "wallpaperdump": 1, "YMS": 2, "ExposurePorn": 4, "RoomPorn": 1, "SkyPorn": 8, "aww": 3, "cars": 21, "wallpaper": 4, "waterporn": 1, "spaceporn": 1, "MH370": 1, "youtubehaiku": 1, "cringepics": 3, "Lightningporn": 2, "WeatherPorn": 2, "gifs": 2, "TopGear": 8, "Houseporn": 1, "battlestations": 28, "Karting": 1, "stormchasing": 7, "meteorology": 1, "pics": 19, "atheism": 7, "AskReddit": 40, "hardstyle": 6, "watchpeopledie": 1, "science": 2, "Seattle": 57, "cringe": 2, "GifSound": 1}
