{"gamemusic": 1, "ShingekiNoKyojin": 1, "Rockband": 3, "fatpeoplehate": 1, "energydrinks": 4, "HeavenlyHost": 1, "MadokaMagica": 3, "reactiongifs": 1, "zelda": 1, "newjersey": 2, "Animesuggest": 7, "wiiu": 3, "twitchplayspokemon": 2, "ps2": 1, "PS3": 4, "vita": 6, "AnimeDeals": 2, "PostYourMAL": 2, "tifu": 1, "PS4": 1, "funny": 2, "ShinMegamiHentai": 1, "visualnovels": 9, "animenocontext": 7, "shittyfoodporn": 3, "AskReddit": 11, "AnimeFigures": 5, "watchinganime": 37, "awwnime": 2, "hockey": 5, "atlus": 1, "pcmasterrace": 1, "animegifs": 1, "gaming": 1, "HunterXHunter": 2, "3DS": 4, "food": 1, "999": 3, "trees": 4, "movies": 1, "Persona5": 3, "gifs": 2, "BlackPeopleTwitter": 2, "animeicons": 5, "animeplot": 3, "ZeroEscape": 3, "truegaming": 1, "persona4golden": 8, "lazylifetips": 1, "nfl": 1, "velvet_room": 1, "Megaten": 13, "terriblefacebookmemes": 3, "AdviceAnimals": 4, "Dakimakuras": 17, "anime": 50, "redditdotcom": 1, "RatchetAndClank": 1, "manga": 7, "PS34": 1}
