{"gardening": 2, "whatisthisthing": 7, "videos": 5, "todayilearned": 6, "tequila": 2, "queen": 1, "Schertz": 1, "funny": 8, "engineering": 1, "woodworking": 2, "news": 7, "SleepApnea": 10, "avionics": 3, "Android": 1, "Newbraunfels": 6, "technology": 1, "AskElectronics": 4, "Psoriasis": 2, "wicked_edge": 15, "roomba": 2, "coins": 2, "AskReddit": 2, "ProtectAndServe": 6, "Enhancement": 4, "sanantonio": 35, "SpaceLaunchSystem": 1, "nasa": 10, "askscience": 1, "HomeImprovement": 18, "mildyinteresting": 1, "guns": 7, "texas": 7, "ShittyEarthPorn": 1, "biology": 2, "AlaskanPorn": 1, "jobs": 8, "TwentyFour": 2, "firefox": 1, "SkyPorn": 12, "aww": 18, "homedefense": 1, "ParrotHeads": 2, "snackexchange": 3, "aviationmaintenance": 8, "PandR": 1, "oddlysatisfying": 1, "landscaping": 4, "americandad": 3, "Workbenches": 4, "whereisthis": 1, "LifeProTips": 3, "Plumbing": 4, "aviation": 44, "321": 14, "howto": 4, "DealsReddit": 2, "coasttocoastam": 4, "artbellsdarkmatter": 4, "science": 1, "homeowners": 1, "politics": 1, "alaska": 24, "pics": 17, "Silverbugs": 2, "AdviceAnimals": 1, "gs2skyrocket": 1, "knives": 21, "blackberry": 10, "Images": 14}
