{"mildlyinteresting": 1, "gardening": 5, "dataisbeautiful": 15, "videos": 31, "gaming": 1, "todayilearned": 73, "HistoryPorn": 1, "gadgets": 2, "interestingasfuck": 1, "conspiracy": 3, "ImaginaryLandscapes": 1, "EarthPorn": 1, "politics": 3, "tifu": 2, "technology": 17, "trashy": 2, "funny": 31, "privacy": 1, "hardcoreaww": 1, "AdviceAnimals": 40, "Showerthoughts": 1, "RoomPorn": 1, "environment": 1, "Autos": 3, "LearnUselessTalents": 2, "WTF": 7, "worldnews": 13, "pcmasterrace": 2, "explainlikeimfive": 1, "Futurology": 3, "firefly": 2, "fatpeoplehate": 1, "facepalm": 1, "YouShouldKnow": 1, "veganfitness": 3, "asmr": 1, "aww": 4, "reactiongifs": 2, "photography": 1, "JusticePorn": 3, "movies": 2, "oddlysatisfying": 1, "unintentionalASMR": 1, "Unexpected": 1, "BlackPeopleTwitter": 2, "Roadcam": 1, "news": 13, "UFOs": 3, "undelete": 2, "thewalkingdead": 10, "gifs": 26, "television": 4, "TopGear": 1, "Frugal": 7, "worldpolitics": 3, "science": 14, "pics": 17, "atheism": 6, "WatchItForThePlot": 1, "AskReddit": 16, "books": 4, "BeforeNAfterAdoption": 1, "ImGoingToHellForThis": 3, "DIY": 1}
