{"Boobies": 2, "HappyEmbarrassedGirls": 1, "TightShirts": 1, "AdviceBoobs": 1, "ModelsGoneMild": 1, "SexyButNotPorn": 5, "gentlemanboners": 5, "futanari": 1, "community": 1, "JessicaNigri": 3, "shittyrobots": 1, "burstingout": 1, "bimbofetish": 1, "sexygirlsinjeans": 1, "christinahendricks": 1, "TheAngieCompetition": 1, "funny": 2, "cosplay": 1, "GirlsInTightShirts": 7, "StretchingIt": 2, "wow": 1, "charactercrossovers": 1, "WtSSTaDaMiT": 1, "AlisonBrie": 1, "FineLadies": 1, "SoFuckable": 5, "superheroinesdefeated": 1, "ass": 1, "theratio": 3, "SexyTummies": 1, "Anna_Faith": 1, "HighHeels": 1, "Cynicalbrit": 1, "kateupton": 1, "fitgirls": 19, "blondehairblueeyes": 3, "news": 1, "doppelbangher": 1, "assinthong": 1, "bustyasians": 1, "cosplaygirls": 5, "gentlemanbonersgifs": 1, "pics": 1, "countrygirls": 1, "Denise_Milani": 1, "EmmaWatson": 2, "Blonde": 2, "BustyPetite": 26, "starlets": 1}
