{"gamevideos": 2, "videos": 4, "youtube": 1, "nintendo": 1, "FreeProWrestling": 9, "Club_Nintendo": 3, "gamecollecting": 8, "Music": 1, "wiiu": 1, "bleachshirts": 3, "funny": 1, "mymusic": 2, "LetsPlayCritiques": 10, "SquaredCircle": 55, "AdviceAnimals": 1, "WTF": 1, "GamerVideos": 7, "letsplay": 40, "IndyWrestling": 2, "gaming": 2, "ZacAttack": 5, "Omaha": 2, "TMNT": 2, "promos": 1, "cringepics": 1, "fxfl": 28, "WredditSchool": 31, "VideoEditing": 5, "GameTheorists": 1, "desmoines": 1, "WredditTV": 1, "wwenetwork": 3, "CFB": 12, "uvtrade": 40, "prowrestling": 2, "pics": 1, "AskReddit": 8, "EntranceThemes": 1, "cky": 1}
