{"KSU": 56, "mildlyinteresting": 1, "help": 2, "videos": 2, "todayilearned": 1, "foxes": 5, "sysadmin": 1, "tipofmytongue": 4, "Music": 3, "proper": 1, "politics": 2, "technology": 1, "funny": 3, "atheism": 1, "space": 1, "furry": 3, "IAmA": 3, "WTF": 2, "Bestof2011": 2, "worldnews": 1, "Atlanta": 23, "explainlikeimfive": 5, "wallpapers": 1, "gaming": 2, "offmychest": 1, "Georgia": 2, "aww": 6, "Dogfort": 1, "germanshepherds": 1, "porterrobinson": 3, "Austin": 4, "pics": 6, "bayarea": 1, "movies": 4, "AskReddit": 4, "digimon": 7, "trance": 45, "ImGoingToHellForThis": 1, "LGG3": 3}
