{"CombatFootage": 5, "mildlyinteresting": 1, "pcgaming": 1, "dataisbeautiful": 1, "TrueReddit": 1, "todayilearned": 1, "reactiongifs": 1, "Battlefield_4_CTE": 2, "hardware": 1, "AnimalsBeingBros": 1, "Showerthoughts": 1, "h1z1": 1, "webdev": 2, "politics": 1, "Android": 4, "technology": 2, "Foodforthought": 1, "Nexus7": 2, "nsfw_wtf": 1, "funny": 6, "MURICA": 1, "backpacking": 3, "space": 4, "trance": 2, "hardcoreaww": 1, "firefox": 2, "Documentaries": 2, "MorbidReality": 3, "aww": 1, "gamedev": 1, "WTF": 3, "worldnews": 1, "pcmasterrace": 2, "GuiltyPleasureMusic": 1, "talesfromtechsupport": 2, "videos": 2, "bestof": 2, "electronicmusic": 2, "Cyberpunk": 1, "verizon": 66, "battlefield3": 2, "food": 1, "askscience": 1, "carriers": 2, "GlobalOffensive": 1, "battlefield_4": 6, "gifs": 3, "netflix": 1, "EQNext": 4, "programming": 1, "pics": 8, "offbeat": 2, "AdviceAnimals": 8, "civ": 7, "techsupport": 13, "Monitors": 1, "history": 1}
