{"BPD": 25, "moraldilemmas": 3, "todayilearned": 2, "WeAreTheMusicMakers": 3, "confession": 2, "redditgetsdrawn": 2, "selfharm": 14, "dadjokes": 1, "korrasami": 5, "spiderbro": 2, "tifu": 2, "iranianmusic": 4, "makorra": 1, "TheLastAirbender": 4, "relationships": 5, "funny": 13, "Israel": 2, "ConfessionBear": 10, "awfuleyebrows": 7, "DestinyTheGame": 1, "AdviceAnimals": 5, "Showerthoughts": 3, "FifthWorldPics": 1, "unexpectedjihad": 2, "TumblrAtRest": 3, "gaming": 1, "facepalm": 2, "iran": 4, "trashy": 1, "Music": 1, "aww": 3, "SuicideWatch": 30, "de": 50, "circlejerk": 33, "smashbros": 1, "MadeOfStyrofoam": 2, "germany": 5, "LifeWithIgor": 1, "MapPorn": 1, "cringepics": 1, "de_IAmA": 3, "WorldMusic": 3, "gifs": 1, "Unexpected": 1, "creepyPMs": 2, "rage": 1, "pics": 9, "atheism": 69, "Glitch_in_the_Matrix": 15, "AskReddit": 44, "TumblrInAction": 10, "SubredditDrama": 6, "trippinthroughtime": 1, "cringe": 2}
