{"CombatFootage": 3, "mildlyinteresting": 1, "A858DE45F56D9BC9": 1, "videos": 2, "insurgency": 11, "Boxing": 1, "playrust": 2, "Justrolledintotheshop": 1, "slavs_squatting": 1, "h1z1": 2, "skateboarding": 16, "TrackMania": 2, "funny": 20, "SpeedRunnersGame": 1, "NBA2k": 1, "DatGuyLirik": 4, "Drifting": 3, "assaultcube": 1, "Documentaries": 2, "AwesomeCarMods": 1, "Autos": 1, "hockey": 4, "nonononoyes": 1, "Astronomy": 1, "assettocorsa": 5, "leagueoflegends": 1, "FRC": 2, "MilitaryPorn": 2, "GlobalOffensive": 135, "aww": 6, "cars": 2, "hockeyplayers": 4, "unturned": 3, "malelivingspace": 1, "oddlysatisfying": 9, "Shitty_Car_Mods": 7, "explainlikeimfive": 3, "linuxmasterrace": 1, "Steam": 4, "Summit1G": 1, "EDC": 3, "TopGear": 11, "Stance": 1, "simracing": 7, "csgobetting": 75, "programming": 1, "LeftHanging": 1, "blog": 1, "AskReddit": 44, "GameDeals": 5, "battlestations": 6, "punchablefaces": 1}
