{"FIFA": 6, "buildapc": 1, "pcgaming": 6, "teenagers": 16, "ShouldIbuythisgame": 14, "PleX": 1, "gadgets": 1, "sgsflair": 4, "cordcutters": 1, "books": 4, "rtzon": 1, "nba": 1, "PS4": 1, "funny": 7, "DunderMifflin": 2, "mountandblade": 1, "AskHistorians": 3, "49ers": 1, "breakingbad": 1, "AdviceAnimals": 4, "pcmasterrace": 33, "soccer": 2, "gaming": 4, "buildapcsales": 1, "titanfall": 1, "patientgamers": 16, "Games": 10, "oblivion": 1, "LifeProTips": 1, "Fitness": 38, "indiegameswap": 1, "Steam": 5, "truegaming": 10, "Morrowind": 1, "television": 6, "SteamGameSwap": 18, "nfl": 1, "pics": 1, "movies": 7, "AskReddit": 7, "GameDeals": 6, "Sat": 4}
