{"IDAP": 1, "Smite": 2, "ghibli": 1, "RandomActsOfGaming": 1, "Psychonaut": 1, "MadeMeSmile": 1, "PublicFreakout": 2, "electronic_cigarette": 1, "rickandmorty": 1, "funhaus": 1, "InternetIsBeautiful": 3, "gaybros": 1, "MDMA": 3, "Yogscast": 1, "nostalgia": 1, "Showerthoughts": 2, "harrypotter": 1, "todayilearned": 1, "woahdude": 1, "WTF": 17, "SoccerBetting": 2, "scifi": 1, "childfree": 1, "normalboots": 1, "food": 5, "horror": 1, "trees": 49, "smashbros": 1, "ImaginaryWesteros": 1, "thewalkingdead": 1, "techsupportgore": 1, "freebies": 2, "AskReddit": 4, "Hypothyroidism": 1, "Cyberpunk": 1, "grilledcheese": 3, "malelifestyle": 2, "StarWars": 1, "unitedkingdom": 1, "spongebob": 1, "NetflixBestOf": 4, "stencils": 1, "AgMarketplace": 1, "DCcomics": 1, "books": 2, "friendsafari": 1, "changemyview": 1, "roosterteeth": 10, "depression": 1, "LSD": 4, "drunkencookery": 2, "lotr": 1, "shittyfoodporn": 7, "AdviceAnimals": 1, "DarkNetMarkets": 3, "TokeSpot": 1, "leagueoflegends": 1, "foodhacks": 2, "MonsterHunter": 7, "disney": 1, "tattoos": 1, "AnimalCrossing": 2, "lgbt": 4, "ImageStabilization": 1, "news": 1, "Unexpected": 1, "ThriftStoreHauls": 1, "pics": 17, "learnart": 1, "GenerationGap": 5, "Constantine": 2, "buildapc": 6, "drunk": 3, "uktrees": 7, "jailbreak": 2, "patientgamers": 1, "community": 1, "Club_Nintendo": 1, "Music": 1, "gaymers": 2, "tifu": 1, "pokemon": 3, "graphic_design": 2, "DnD": 1, "FiftyFifty": 3, "Drugs": 2, "led_zeppelin": 1, "Illustration": 1, "MorbidReality": 2, "195": 1, "WebGames": 1, "doodles": 2, "Fallout": 2, "3DS": 5, "gamegrumps": 14, "mildlyinfuriating": 1, "breakingmom": 1, "somethingimade": 1, "Cigarettes": 1, "TopGear": 2, "MapPorn": 1, "millionairemakers": 1, "Marvel": 4, "television": 1, "SteamGameSwap": 2, "rage": 3, "makemychoice": 3, "PerfectTiming": 1, "movies": 8, "civ": 3, "LGBTeens": 4, "KerbalSpaceProgram": 1, "BritishSuccess": 2, "GetStudying": 1, "FoodPorn": 2, "awesome": 1, "sushi": 1, "teenagers": 10, "FanTheories": 1, "AmericanHorrorStory": 5, "Internet_Box": 2, "Pizza": 2, "funny": 15, "IAmA": 2, "DrugStashes": 1, "animation": 1, "PS4": 2, "britishproblems": 8, "saplings": 2, "MoviePosterPorn": 3, "gaming": 32, "Frozen": 2, "FantasyLife3ds": 1, "nerdcubed": 3, "Games": 1, "LifeWithIgor": 1, "nintendo": 1, "CringeAnarchy": 2, "TrueFilm": 1, "atheism": 2, "secretsanta": 2, "drawing": 1, "shutupandtakemymoney": 1}
