{"HalfLife": 2, "gamemusic": 2, "indie": 3, "TheseAreOurAlbums": 1, "TrueAskReddit": 1, "SJSU": 3, "SanJose": 18, "FinalFantasy": 8, "Music": 10, "jeffgoldblum": 1, "assassinscreed": 7, "tf2": 2, "Guitar": 2, "Xcom": 2, "earthbound": 27, "OutOfTheLoop": 1, "IAmA": 3, "chronotrigger": 5, "santacruz": 4, "gopro": 1, "bayareashows": 2, "leagueoflegends": 1, "Magfest": 5, "JRPG": 2, "gaming": 2, "LosAngeles": 1, "GODZILLA": 35, "nerdfighters": 3, "portlandmusic": 1, "somethingimade": 2, "gamesuggestions": 1, "SFMusic": 10, "Games": 1, "bandmembers": 95, "askmusicians": 1, "doctorwho": 9, "Twitch": 4, "starcraft": 1, "chiptunes": 1, "gamingsuggestions": 8, "sanfrancisco": 1, "WeAreTheMusicMakers": 95, "AskReddit": 16, "ratemyband": 7, "guitarpedals": 4, "lifeisstrange": 12, "retrogaming": 1, "vinyl": 1}
