{"Paleo": 1, "nursing": 2, "Bandnames": 1, "Dallas": 14, "todayilearned": 4, "xxfitness": 7, "emergencymedicine": 1, "Cooking": 11, "sex": 21, "books": 1, "TwoXChromosomes": 125, "politics": 6, "ShitRedditSays": 1, "TrollXFitness": 1, "funny": 1, "Coffee": 2, "gameofthrones": 2, "TrueReddit": 6, "SRSWomen": 1, "neopagan": 1, "IAmA": 1, "craftit": 2, "ProtectAndServe": 1, "ForTwenty": 2, "environment": 1, "picrequests": 2, "scifi": 1, "WTF": 1, "texas": 9, "Baking": 4, "reddit.com": 3, "aww": 4, "OkCupid": 21, "oddlysatisfying": 1, "Frugal": 2, "wikipedia": 1, "food": 3, "Fitness": 4, "news": 2, "Austin": 29, "keto": 1, "lgbt": 1, "pics": 1, "offbeat": 3, "AskReddit": 48, "ems": 42, "polyamory": 25, "NPR": 1}
