{"houston": 25, "osx": 1, "MadeMeSmile": 7, "PleX": 2, "SHSU": 2, "Foodforthought": 4, "AskMen": 12, "girlsgonewired": 1, "startrek": 2, "writing": 1, "sanantonio": 3, "reddit_news": 3, "texas": 2, "YouShouldKnow": 2, "gifs": 1, "UpliftingNews": 4, "HomeNetworking": 2, "geek": 9, "Jokes": 1, "NoStupidQuestions": 1, "LinuxActionShow": 1, "Art": 2, "pcmasterrace": 1, "photoshopbattles": 6, "itsaunixsystem": 3, "dadjokes": 4, "AdviceAnimals": 3, "techsupport": 17, "ColorizedHistory": 1, "google": 8, "AskWomen": 8, "NetflixBestOf": 2, "InsightfulQuestions": 2, "netneutrality": 2, "changemyview": 4, "GetStudying": 1, "Android": 8, "openwrt": 9, "humor": 5, "androiddev": 2, "Lubuntu": 4, "socialskills": 1, "leagueoflegends": 1, "electronics": 1, "CutYourOwnHair": 3, "AskReddit": 29, "drums": 1, "linux_gaming": 1, "shittyprogramming": 2, "CasualMath": 2, "apple": 13, "TrueReddit": 3, "Dallas": 7, "linux": 20, "iiiiiiitttttttttttt": 1, "GIMP": 3, "computertechs": 1, "OutOfTheLoop": 2, "HoustonClassifieds": 1, "musictheory": 4, "explainlikeimfive": 1, "snowden": 1, "cordcutters": 12, "web_design": 1, "NeutralPolitics": 2, "Austin": 3, "ProgrammerHumor": 14, "gadgets": 5, "findareddit": 2, "softwaregore": 5, "hacking": 2, "windowsphone": 11, "DecidingToBeBetter": 2, "sysadmin": 5, "learnprogramming": 1, "technology": 5, "HouseOfCards": 1, "productivity": 1, "ShitRedditSays": 1, "TechNewsToday": 2, "wallpapers": 1, "talesfromtechsupport": 16, "DailyTechNewsShow": 1, "raspberry_pi": 3, "Futurology": 5, "mac": 1, "RioGrandeValley": 1, "FortWorth": 2, "tech": 3, "coys": 1, "tall": 39, "microsoft": 1}
