{"mildlyinteresting": 9, "pcgaming": 9, "whatisthisthing": 5, "videos": 2, "todayilearned": 1, "WarOnComcast": 1, "VolleyballGirls": 3, "InternetIsBeautiful": 1, "KotakuInAction": 78, "gadgets": 2, "IdiotsFightingThings": 1, "Justrolledintotheshop": 9, "woodworking": 11, "perfectloops": 5, "PussyPass": 3, "news": 1, "politics": 11, "technology": 1, "funny": 12, "girlsinyogapants": 1, "Robocraft": 6, "cosplay": 1, "space": 1, "self": 1, "IAmA": 1, "AskReddit": 2, "Showerthoughts": 3, "secretsanta": 1, "AnimalsBeingJerks": 1, "Awww": 1, "woahdude": 3, "WorldofTanks": 2, "networking": 11, "lifehacks": 4, "explainlikeimfive": 2, "talesfromtechsupport": 2, "gaming": 8, "cablefail": 5, "WTF": 6, "gifs": 6, "aww": 2, "lawncare": 3, "HomeNetworking": 7, "dresdenfiles": 6, "AgainstGamerGate": 10, "Unexpected": 6, "LifeProTips": 1, "KerbalSpaceProgram": 5, "Cisco": 5, "GamerGhazi": 1, "Scotch": 11, "evolutionReddit": 1, "conduitporn": 2, "oddlysatisfying": 3, "AbandonedPorn": 3, "cosplaybutts": 4, "dayz": 21, "KiAChatroom": 4, "dayzlfg": 1, "techsupportgore": 1, "WatchItForThePlot": 15, "makemychoice": 2, "dataisbeautiful": 1, "creepy": 8, "pics": 11, "cosplaygirls": 9, "AdviceAnimals": 23, "TumblrInAction": 8, "tech": 2, "photoshopbattles": 1, "CosplayBoobs": 1, "whitepeoplegifs": 2, "ImGoingToHellForThis": 1, "cableporn": 11}
