{"Paleo": 6, "gardening": 2, "DessertPorn": 1, "biology": 9, "CityPorn": 1, "TrollXChromosomes": 10, "mildlyinteresting": 1, "sex": 6, "cocktails": 1, "rant": 14, "conspiratard": 5, "conspiracy": 3, "creepy": 1, "TwoXChromosomes": 25, "entwives": 3, "OneY": 11, "technology": 1, "againstmensrights": 11, "whatisthisthing": 4, "relationships": 30, "badphilosophy": 2, "TheBluePill": 39, "mycology": 2, "BestOfOutrageCulture": 11, "nature": 1, "EverythingScience": 1, "Dinosaurs": 1, "openbroke": 1, "animation": 3, "raisedbynarcissists": 15, "musictheory": 1, "ftm": 1, "sorceryofthespectacle": 1, "offmychest": 1, "Cooking": 4, "SRSDiscussion": 12, "lostgeneration": 8, "asoiaf": 4, "feminisms": 6, "GamerGhazi": 56, "SRSWomen": 2, "ShitRedditSays": 2, "whatsthisbird": 2, "KitchenConfidential": 1, "science": 10, "leaves": 1, "museum": 1, "piercing": 2, "relationship_advice": 54, "Hair": 1, "AgainstGamerGate": 6, "ShadowBanned": 1, "MakeupAddiction": 3, "hotguyswithtattoos": 1, "Portland": 19, "mythology": 1, "discordian": 2, "marijuanaenthusiasts": 1}
