{"Cyberpunk_Music": 28, "UrbanHell": 1, "FoodPorn": 6, "CityPorn": 2, "buffy": 5, "cyberpunk_stories": 1, "dadjokes": 4, "books": 15, "southpark": 22, "funny": 11, "Coffee": 2, "drunkencookery": 130, "thebutton": 18, "shittyfoodporn": 5, "IAmA": 1, "AdviceAnimals": 10, "Showerthoughts": 1, "writing": 23, "beer": 1, "woahdude": 1, "gaming": 11, "wroteabook": 2, "glitch_art": 5, "sciencefiction": 2, "trashy": 3, "selfpublish": 2, "ebookdeals": 1, "aww": 1, "trees": 9, "AntiJokes": 14, "ShowOffYourCharacter": 1, "scifiwriting": 1, "Psychonaut": 1, "indieauthorpromotions": 2, "comicbooks": 23, "EntTreats": 6, "treemusic": 26, "worldbuilding": 4, "showerbeer": 4, "steampunk": 1, "movies": 2, "standupshots": 8, "HomestarRunner": 2, "Cyberpunk": 6, "science": 1}
