{"wethejury": 1, "ChronicPain": 3, "whatisthisthing": 3, "videos": 2, "DoesAnybodyElse": 5, "todayilearned": 1, "Porsche": 3, "reactiongifs": 1, "homegrowntits": 1, "burstingout": 1, "interestingasfuck": 1, "tipofmytongue": 8, "plastidip": 99, "InternetIsBeautiful": 2, "technology": 1, "ecommerce": 1, "carporn": 1, "MorbidReality": 1, "fullmoviesonyoutube": 2, "funny": 3, "crossfit": 1, "IAmA": 4, "Showerthoughts": 2, "ITunes": 1, "Hotchickswithtattoos": 1, "thewalkingdead": 3, "WTF": 18, "AlienBlue": 3, "Standup": 7, "watchpeopledie": 4, "explainlikeimfive": 2, "howardstern": 108, "Boobies": 1, "fatpeoplehate": 1, "StandUpComedy": 3, "Stacked": 1, "voluptuous": 1, "gonewild": 1, "cars": 11, "NSFW_GIF": 1, "howto": 1, "answers": 6, "FlashingGirls": 1, "Fitness": 3, "Austin": 24, "gettingherselfoff": 1, "ipad": 2, "gifs": 2, "television": 2, "pranks": 1, "BurningMan": 1, "rage": 1, "Watches": 3, "pics": 2, "movies": 7, "AskReddit": 46, "legaladvice": 4, "zombies": 1, "FloridaMan": 2, "Seiko": 1}
