{"videos": 3, "FoodPorn": 2, "todayilearned": 2, "ConsumerGallery": 1, "columbusmusic": 7, "Filmmakers": 20, "shrooms": 8, "RandomKindness": 5, "musicfestivals": 1, "DeepIntoYouTube": 1, "radioreddit": 2, "Ohio": 4, "politics": 2, "news": 6, "orangered": 5, "depression": 1, "ExtraLife": 2, "CableMike": 4, "funny": 4, "Columbus": 10, "ThisIsOurMusic": 21, "Bad_Cop_No_Donut": 1, "Warthunder": 8, "IAmA": 7, "AdviceAnimals": 9, "blog": 2, "aquaponics": 6, "santashelpers": 1, "WarThunderRDDTWing": 9, "imaginedragons": 1, "boston": 8, "TheDarkTower": 3, "scifi": 16, "gaming": 2, "BioshockInfinite": 5, "WTF": 17, "aww": 3, "atheism": 1, "Eve": 3, "Teachers": 3, "Psychonaut": 4, "climbing": 48, "blunderyears": 1, "Ingress": 2, "motorcycles": 4, "daria": 1, "BandCamp": 2, "pics": 1, "WeAreTheMusicMakers": 10, "AskReddit": 18, "secretsanta": 2, "Music": 3, "shittyfoodporn": 1, "CafeRacers": 5}
