{"ExpectationVsReality": 2, "motivation": 1, "shittyama": 1, "drunk": 4, "todayilearned": 1, "Bacon": 5, "adventuretime": 5, "confession": 2, "Aquariums": 3, "sex": 4, "ShitWallsSay": 1, "Music": 1, "canadients": 4, "entOttawa": 21, "skiing": 11, "Baking": 1, "Pieces": 8, "pokemon": 1, "tattoo": 1, "firstworldanarchists": 1, "funny": 13, "longboarding": 6, "townofbanff": 1, "Cheap_Meals": 1, "Drugs": 1, "EatCheapAndHealthy": 3, "IAmA": 2, "nostalgia": 1, "barrie": 3, "food": 1, "StonerEngineering": 3, "beer": 1, "badtattoos": 1, "FoodPorn": 1, "AdviceAnimals": 2, "WTF": 7, "saplings": 1, "doodles": 1, "fffffffuuuuuuuuuuuu": 5, "wallpapers": 1, "randomactsofdrawing": 1, "tattoos": 16, "StonerProTips": 5, "trippy": 6, "shutupandtakemymoney": 1, "Trucks": 2, "TattooDesigns": 1, "RandomKindness": 1, "casualiama": 24, "Ladybonersgonecuddly": 1, "howto": 1, "trees": 43, "cats": 3, "Pokeents": 2, "LadyBoners": 1, "LifeProTips": 1, "TheGirlSurvivalGuide": 1, "doctorwho": 2, "illusionporn": 1, "alcohol": 6, "photoshopbattles": 2, "asktrees": 17, "Drawit": 3, "BostonBruins": 1, "leaves": 1, "canadia": 1, "ottawa": 10, "pics": 8, "PerfectTiming": 1, "findareddit": 1, "AskReddit": 35, "secretsanta": 3, "blackberry": 3, "sloths": 1, "snowboarding": 8, "TreesAMAA": 1, "GetMotivated": 1, "Cartalk": 1}
