{"mildlyinteresting": 1, "TrueAtheism": 5, "unitedkingdom": 44, "videos": 14, "todayilearned": 9, "gentlemanboners": 4, "TheSimpsons": 3, "hiphopheads": 1, "60fpsporn": 1, "Conservative": 4, "conspiracy": 1, "Music": 1, "gifs": 3, "politics": 3, "ContagiousLaughter": 1, "SFWPornGifs": 1, "technology": 1, "NormMacdonald": 1, "funny": 32, "gameofthrones": 2, "ColorBlind": 2, "softies": 1, "movies": 3, "shittyfoodporn": 1, "TrueReddit": 1, "IAmA": 1, "AdviceAnimals": 8, "Showerthoughts": 13, "aww": 1, "AngieVaronaLegal": 1, "Libertarian": 1, "woahdude": 1, "britishproblems": 4, "nottheonion": 3, "reddevils": 3, "Hot_Women_Gifs": 1, "soccer": 120, "europe": 2, "gaming": 1, "WTF": 6, "ArianaGrande": 1, "food": 1, "Futurology": 1, "footballmanagergames": 3, "beerporn": 2, "madmen": 1, "worldnews": 8, "BlackPeopleTwitter": 1, "news": 6, "rickandmorty": 1, "lewronggeneration": 3, "gonewild": 1, "television": 11, "WatchItForThePlot": 1, "Celebs": 7, "pics": 11, "behindthegifs": 1, "AskReddit": 4, "ukpolitics": 12, "NoShitSherlock": 1, "london": 2, "cringe": 9, "EmmaWatson": 6}
