{"mildlyinteresting": 3, "TrueAtheism": 1, "technews": 2, "MitchellAndWebb": 1, "gaming": 5, "InternetIsBeautiful": 1, "SubredditDrama": 14, "oddlysatisfying": 2, "BuyItForLife": 1, "RedditThroughHistory": 3, "politics": 19, "unitedkingdom": 10, "Damnthatsinteresting": 6, "funny": 26, "OldSchoolCool": 5, "britishproblems": 1, "behindthegifs": 1, "museum": 4, "BritishTV": 10, "vgb": 20, "SubredditDramaDrama": 2, "woahdude": 6, "WTF": 27, "WebGames": 16, "worldnews": 3, "MechanicalKeyboards": 1, "nonononoyes": 1, "Pareidolia": 3, "architecture": 2, "europe": 6, "GTA": 2, "VicAndBob": 1, "misleadingthumbnails": 1, "sniperelite": 9, "aww": 1, "Futurology": 2, "gamernews": 3, "30ROCK": 11, "vegas": 27, "AskReddit": 13, "ImageStabilization": 2, "news": 2, "ainbow": 2, "fatherted": 2, "illusionporn": 2, "RoomPorn": 1, "gifs": 12, "quiteinteresting": 3, "calvinandhobbes": 2, "comics": 2, "pics": 14, "atheism": 5, "4chan": 51, "AdviceAnimals": 26, "tech": 1, "wheredidthesodago": 1, "zombies": 3, "KimmySchmidt": 17, "GameDeals": 1, "ifiwonthelottery": 3, "eyebombing": 1}
