{"UrbanHell": 5, "ArtisanVideos": 5, "chemicalreactiongifs": 1, "WhiteNationalism": 5, "interestingasfuck": 5, "InfrastructurePorn": 1, "Foodforthought": 56, "space": 2, "distension": 1, "startrek": 12, "justneckbeardthings": 5, "merica": 7, "mobydick": 1, "seaporn": 2, "trailerparkboys": 28, "HybridAnimals": 1, "MilitaryGfys": 1, "medicalschool": 20, "breathinginformation": 4, "Borgasm": 1, "Wellthatsucks": 5, "news": 3, "Alabama": 5, "Nationals": 15, "gifs": 13, "Unexpected": 2, "TaylorSwiftPictures": 1, "science": 7, "freebies": 1, "cripplingalcoholism": 128, "nasa": 8, "Birmingham": 53, "wheredidthesodago": 1, "uchicago": 20}
