{"dancemoms": 18, "weddingplanning": 3, "Cello": 1, "videos": 5, "talesfromcallcenters": 2, "todayilearned": 2, "DowntonAbbey": 4, "medical": 1, "ShitCosmoSays": 2, "AmISexy": 3, "TwoXChromosomes": 3, "ADHD": 38, "femalefashionadvice": 1, "depression": 5, "relationships": 29, "funny": 6, "BALLET": 1, "languagelearning": 5, "camping": 1, "chicago": 2, "SkincareAddiction": 11, "acne": 2, "orchestra": 3, "AskReddit": 64, "violinist": 78, "transpassing": 1, "poodles": 4, "WTF": 4, "misophonia": 13, "Vegetarianism": 2, "NoPoo": 3, "dogs": 12, "Anxiety": 13, "classicalmusic": 5, "relationship_tips": 5, "facepalm": 7, "legaladvice": 4, "vegan": 2, "LifeProTips": 8, "wedding": 7, "creepyPMs": 3, "gifs": 1, "ProjectRunway": 3, "PrettyLittleLiars": 4, "rant": 2, "Dance": 3, "vegetarian": 4, "chicagojobs": 1, "SkincareAddicts": 1, "AdviceAnimals": 15, "StopSelfHarm": 1, "travel": 3, "RealEstate": 4}
