{"FIFA": 38, "shallowhouse": 1, "videos": 7, "todayilearned": 1, "reactiongifs": 1, "Gotham": 1, "books": 2, "Music": 9, "everymanshouldknow": 1, "tifu": 2, "technology": 1, "funny": 11, "Twitch": 1, "movies": 1, "trance": 49, "wow": 15, "IAmA": 5, "AdviceAnimals": 45, "Showerthoughts": 1, "breakingbad": 2, "chess": 1, "WTF": 22, "worldnews": 1, "soccer": 48, "gaming": 15, "hiphopheads": 8, "aww": 2, "industrialmusic": 1, "TheMentalist": 13, "Jokes": 2, "ffxiv": 1, "Fitness": 1, "hearthstone": 2, "news": 1, "AskMen": 1, "creepyPMs": 10, "EBM": 2, "pics": 19, "4chan": 5, "AskReddit": 36, "DotA2": 38, "psytrance": 2}
