{"castlevania": 1, "Catholicism": 3, "normalboots": 1, "gamecollecting": 55, "Music": 11, "wiiu": 22, "ProfessorLayton": 3, "pics": 3, "pokemon": 2, "funny": 9, "Michigan": 10, "Flute": 3, "zelda": 3, "amiibo": 143, "AdviceAnimals": 3, "worldnews": 1, "gaming": 7, "AmiiboMichigan": 10, "gamegrumps": 15, "smashbros": 19, "lightsalot": 5, "Dreamtheater": 6, "nintendo": 9, "news": 5, "MTU": 4, "Steam": 2, "thewalkingdead": 14, "gifs": 1, "science": 2, "fireemblem": 28, "Gamecube": 3, "Purityring": 3, "AskReddit": 9, "GlobalOffensive": 2, "Games": 3, "retrogaming": 4, "OutOfTheLoop": 1}
